test.py
sugarpowder/__init__.py
sugarpowder/dates.py
sugarpowder/infixes.py
sugarpowder/mark_time.py
sugarpowder/pipes.py
sugarpowder/serialization.py
sugarpowder/utils.py
sugarpowder/witherr.py
sugarpowder/zmap.py
sugarpowder-1.3.0.dist-info/LICENSE
sugarpowder-1.3.0.dist-info/METADATA
sugarpowder-1.3.0.dist-info/WHEEL
sugarpowder-1.3.0.dist-info/top_level.txt
sugarpowder-1.3.0.dist-info/RECORD
