Metadata-Version: 2.1
Name: sugarpowder
Version: 1.3.0
Summary: Package of Python syntactic sugars inspired by Elixir, Go, Rust, Julia, and other languages
Author-email: Geunseong Jung <dreamwayjgs@gmail.com>
License: MIT License
Project-URL: Homepage, https://github.com/dreamwayjgs/sugarpowder
Project-URL: Bug Tracker, https://github.com/dreamwayjgs/sugarpowder/issues
Classifier: Programming Language :: Python :: 3
Classifier: License :: OSI Approved :: MIT License
Classifier: Operating System :: OS Independent
Requires-Python: >=3.10
License-File: LICENSE
Requires-Dist: pandas>=2.0.0
Requires-Dist: pyarrow
Requires-Dist: blosc
Requires-Dist: dill
